pype/__init__.py
pype/helpers.py
pype/infix.py
pype/numpy_helpers.py
pype/optimize.py
pype/optimize_old.py
pype/optimize_old_with_replace.py
pype/test_optimize.py
pype/test_pypeval.py
pype/time_helpers.py
pype/val_wrapper.py
pype/vals.py
python_pype_lang-1.2.0.dist-info/DESCRIPTION.rst
python_pype_lang-1.2.0.dist-info/METADATA
python_pype_lang-1.2.0.dist-info/RECORD
python_pype_lang-1.2.0.dist-info/WHEEL
python_pype_lang-1.2.0.dist-info/metadata.json
python_pype_lang-1.2.0.dist-info/top_level.txt
