Metadata-Version: 2.0
Name: python-pype-lang
Version: 1.2.0
Summary: Python-integrated functional programming language - Provides easy-to-use pseudo-macros for common functional programming tasks such as maps, reduces, filters, conditionals, dictionary manipulations, and list manipulations..
Home-page: https://github.com/bbbdragon/python-pype-lang
Author: Bennett Charles Bullock
Author-email: bennettbullock36@gmail.com
License: MIT
Keywords: functional programming map reduce filter lambda conditional
Platform: UNKNOWN
Classifier: Development Status :: 3 - Alpha
Classifier: License :: OSI Approved :: MIT License
Classifier: Programming Language :: Python :: 3.6
Classifier: Operating System :: OS Independent
Requires-Dist: numpy
Requires-Dist: astpretty
Requires-Dist: python-dateutil
